<annotation>
    <folder>images</folder>
    <filename>079e0f6e-1009-4a7a-aa4f-43a2658b4b1f</filename>
    <source>
        <database>Unknown</database>
    </source>
    <size>
        <width>600</width>
        <height>800</height>
        <depth>3</depth>
    </size>
    <segmented>0</segmented>
    <object>
        <name>licenseplates</name>
        <pose>Unspecified</pose>
        <truncated>0</truncated>
        <difficult>0</difficult>
        <bndbox>
            <xmin>551.7180442810059</xmin>
            <ymin>286.69166564941406</ymin>
            <xmax>494.7896361351013</xmax>
            <ymax>188.68650197982788</ymax>
        </bndbox>
    </object>
</annotation>